errortranslator/__init__.py
simarpreet_error_translator-0.1.0.dist-info/METADATA
simarpreet_error_translator-0.1.0.dist-info/WHEEL
simarpreet_error_translator-0.1.0.dist-info/top_level.txt
simarpreet_error_translator-0.1.0.dist-info/RECORD
