Metadata-Version: 2.4
Name: simarpreet-error-translator
Version: 0.1.0
Summary: Explains Python errors simply.
Author: Simarpreet Singh
Requires-Dist: requests
